t4/__init__.py
t4/admin.py
t4/api.py
t4/bucket.py
t4/data_transfer.py
t4/exceptions.py
t4/formats.py
t4/imports.py
t4/main.py
t4/packages.py
t4/search_util.py
t4/session.py
t4/util.py
t4/xattr.py
tests/__init__.py
tests/conftest.py
tests/test_api.py
tests/test_bucket.py
tests/test_cli.py
tests/test_data_transfer.py
tests/test_formats.py
tests/test_search.py
tests/test_util.py
tests/utils.py
tests/integration/__init__.py
tests/integration/test_packages.py
t4-0.1.4.dist-info/METADATA
t4-0.1.4.dist-info/WHEEL
t4-0.1.4.dist-info/entry_points.txt
t4-0.1.4.dist-info/top_level.txt
t4-0.1.4.dist-info/RECORD
