Metadata-Version: 2.1
Name: t4
Version: 0.1.4
Summary: T4
Home-page: https://github.com/quiltdata/t4
Author: quiltdata
Author-email: contact@quiltdata.io
License: LICENSE
Platform: UNKNOWN
Classifier: Development Status :: 5 - Production/Stable
Classifier: Intended Audience :: Developers
Classifier: Operating System :: OS Independent
Classifier: Programming Language :: Python
Classifier: Programming Language :: Python :: 3.5
Classifier: Programming Language :: Python :: 3.6
Classifier: Programming Language :: Python :: 3.7
Requires-Dist: appdirs (>=1.4.0)
Requires-Dist: aws-requests-auth (>=0.4.2)
Requires-Dist: boto3 (>=1.8.0)
Requires-Dist: elasticsearch (~=6.3.1)
Requires-Dist: future (>=0.16.0)
Requires-Dist: jsonlines (==1.2.0)
Requires-Dist: numpy (>=1.14.0)
Requires-Dist: packaging (>=16.8)
Requires-Dist: pandas (>=0.19.2)
Requires-Dist: pyarrow (>=0.9.0)
Requires-Dist: requests (>=2.12.4)
Requires-Dist: ruamel.yaml (<=0.15.70)
Requires-Dist: six (>=1.10.0)
Requires-Dist: tqdm (>=4.26.0)
Requires-Dist: urllib3 (<1.25,>=1.21.1)
Requires-Dist: humanize
Requires-Dist: ipywidgets (>=0.6.0)
Requires-Dist: xattr (>=0.9.6) ; platform_system != "Windows"
Requires-Dist: enum34 ; python_version < "3.0"
Requires-Dist: pathlib2 ; python_version <= "3.5"
Provides-Extra: tests
Requires-Dist: codecov ; extra == 'tests'
Requires-Dist: pytest ; extra == 'tests'
Requires-Dist: pytest-cov ; extra == 'tests'
Requires-Dist: responses ; extra == 'tests'
Requires-Dist: tox ; extra == 'tests'
Requires-Dist: detox ; extra == 'tests'
Requires-Dist: tox-pytest-summary ; extra == 'tests'
